setup.cfg
setup.py
SiLens/lime_si.py
SiLens/neighbourhood_effect.py
SiLens.egg-info/PKG-INFO
SiLens.egg-info/SOURCES.txt
SiLens.egg-info/dependency_links.txt
SiLens.egg-info/not-zip-safe
SiLens.egg-info/requires.txt
SiLens.egg-info/top_level.txt