Metadata-Version: 1.0
Name: SiLens
Version: 0.1
Summary: First version of Machine Learning Interpretation tool by SIngulariti
Home-page: http://github.com/singularitiai/SiLens/archive/v0.1.tar.gz
Author: Kanishka Sharma
Author-email: kanishka.sharma@singulariti.ai
License: BSD
Platform: UNKNOWN
